ker/__init__.py
ker/cli.py
ker/core.py
mail_check_jack-0.1.2.dist-info/METADATA
mail_check_jack-0.1.2.dist-info/WHEEL
mail_check_jack-0.1.2.dist-info/entry_points.txt
mail_check_jack-0.1.2.dist-info/top_level.txt
mail_check_jack-0.1.2.dist-info/RECORD
